LICENSE
MANIFEST.in
README.rst
auth.sample
setup.cfg
setup.py
docs/API.rst
docs/Installation.rst
docs/Intro.rst
docs/Makefile
docs/Usage.rst
docs/Web.rst
docs/conf.py
docs/index.rst
docs/make.bat
docs/requirements.txt
docs/_build/doctrees/API.doctree
docs/_build/doctrees/Installation.doctree
docs/_build/doctrees/Intro.doctree
docs/_build/doctrees/Usage.doctree
docs/_build/doctrees/Web.doctree
docs/_build/doctrees/environment.pickle
docs/_build/doctrees/index.doctree
docs/_build/html/.buildinfo
docs/_build/html/API.html
docs/_build/html/Installation.html
docs/_build/html/Intro.html
docs/_build/html/Usage.html
docs/_build/html/Web.html
docs/_build/html/genindex.html
docs/_build/html/index.html
docs/_build/html/objects.inv
docs/_build/html/py-modindex.html
docs/_build/html/search.html
docs/_build/html/searchindex.js
docs/_build/html/_sources/API.txt
docs/_build/html/_sources/Installation.txt
docs/_build/html/_sources/Intro.txt
docs/_build/html/_sources/Usage.txt
docs/_build/html/_sources/Web.txt
docs/_build/html/_sources/index.txt
docs/_build/html/_static/ajax-loader.gif
docs/_build/html/_static/alabaster.css
docs/_build/html/_static/basic.css
docs/_build/html/_static/comment-bright.png
docs/_build/html/_static/comment-close.png
docs/_build/html/_static/comment.png
docs/_build/html/_static/custom.css
docs/_build/html/_static/doctools.js
docs/_build/html/_static/down-pressed.png
docs/_build/html/_static/down.png
docs/_build/html/_static/file.png
docs/_build/html/_static/jquery-1.11.1.js
docs/_build/html/_static/jquery.js
docs/_build/html/_static/minus.png
docs/_build/html/_static/plus.png
docs/_build/html/_static/pygments.css
docs/_build/html/_static/searchtools.js
docs/_build/html/_static/underscore-1.3.1.js
docs/_build/html/_static/underscore.js
docs/_build/html/_static/up-pressed.png
docs/_build/html/_static/up.png
docs/_build/html/_static/websupport.js
twitterbymb/__init__.py
twitterbymb/__main__.py
twitterbymb/twitwall-betamax.py
twitterbymb/twitwall.py
twitterbymb.egg-info/PKG-INFO
twitterbymb.egg-info/SOURCES.txt
twitterbymb.egg-info/dependency_links.txt
twitterbymb.egg-info/entry_points.txt
twitterbymb.egg-info/not-zip-safe
twitterbymb.egg-info/requires.txt
twitterbymb.egg-info/top_level.txt
