Metadata-Version: 1.1
Name: twitterbymb
Version: 0.5.2
Summary: Simple console and web Twitter wall
Home-page: https://github.com/marekbert/MI-PYP1
Author: Marek Bertovic
Author-email: mb.bertovic@gmail.com
License: Public Domain
Platform: UNKNOWN
Classifier: Intended Audience :: Developers
Classifier: License :: OSI Approved :: GNU General Public License v3 (GPLv3)
Classifier: Operating System :: POSIX :: Linux
Classifier: Programming Language :: Python
Classifier: Programming Language :: Python :: 3
Classifier: Programming Language :: Python :: 3.5
Classifier: Topic :: Software Development :: Libraries
